reward_hub/__init__.py
reward_hub/_version.py
reward_hub/base.py
reward_hub/drsow.py
reward_hub/utils.py
reward_hub/hf/__init__.py
reward_hub/hf/reward.py
reward_hub/llm_judge/__init__.py
reward_hub/llm_judge/groupwise.py
reward_hub/llm_judge/pointwise.py
reward_hub/llm_judge/prompts.py
reward_hub/llm_judge/utils.py
reward_hub/openai/__init__.py
reward_hub/openai/reward.py
reward_hub/openai/vllm_client.py
reward_hub/vllm/__init__.py
reward_hub/vllm/reward.py
reward_hub-0.1.7.dist-info/licenses/LICENSE
reward_hub-0.1.7.dist-info/METADATA
reward_hub-0.1.7.dist-info/WHEEL
reward_hub-0.1.7.dist-info/top_level.txt
reward_hub-0.1.7.dist-info/RECORD
