Metadata-Version: 2.4
Name: reward_hub
Version: 0.1.7
Summary: A unified hub for reward models in AI alignment
Author-email: Red Hat AI Innovation <gxxu@redhat.com>
License: Apache-2.0
Project-URL: Homepage, https://github.com/Red-Hat-AI-Innovation-Team/reward_hub/tree/main
Project-URL: Bug Tracker, https://github.com/Red-Hat-AI-Innovation-Team/reward_hub/issues
Classifier: Environment :: Console
Classifier: Programming Language :: Python :: 3
Classifier: Programming Language :: Python :: 3.9
Classifier: Programming Language :: Python :: 3.10
Classifier: Programming Language :: Python :: 3.11
Classifier: Programming Language :: Python :: 3.12
Classifier: License :: OSI Approved :: Apache Software License
Classifier: License :: OSI Approved :: MIT License
Classifier: Operating System :: POSIX :: Linux
Classifier: Topic :: Scientific/Engineering :: Artificial Intelligence
Requires-Python: >=3.9
License-File: LICENSE
Requires-Dist: transformers>=4.53.2
Requires-Dist: numpy
Requires-Dist: requests
Requires-Dist: openai>=1.68.2
Requires-Dist: torch>=2.7.0
Requires-Dist: litellm<1.75.0,>=1.70.0
Requires-Dist: python-dotenv>=1.0.0
Requires-Dist: tenacity>=8.0.0
Provides-Extra: dev
Requires-Dist: pytest>=7.0.0; extra == "dev"
Requires-Dist: pytest-mock>=3.10.0; extra == "dev"
Requires-Dist: pytest-asyncio>=0.21.0; extra == "dev"
Requires-Dist: pre-commit<4.0,>=3.0.4; extra == "dev"
Requires-Dist: ruff>=0.10.0; extra == "dev"
Provides-Extra: vllm
Requires-Dist: vllm>=0.10.0; extra == "vllm"
Provides-Extra: prm
Requires-Dist: vllm>=0.10.0; extra == "prm"
Requires-Dist: transformers==4.53.2; extra == "prm"
Dynamic: license-file
